odoo/addons/sale_stock_picking_blocking/README.rst
odoo/addons/sale_stock_picking_blocking/__init__.py
odoo/addons/sale_stock_picking_blocking/__manifest__.py
odoo/addons/sale_stock_picking_blocking/data/sale_stock_picking_blocking_data.xml
odoo/addons/sale_stock_picking_blocking/i18n/am.po
odoo/addons/sale_stock_picking_blocking/i18n/ar.po
odoo/addons/sale_stock_picking_blocking/i18n/bg.po
odoo/addons/sale_stock_picking_blocking/i18n/bs.po
odoo/addons/sale_stock_picking_blocking/i18n/ca.po
odoo/addons/sale_stock_picking_blocking/i18n/cs.po
odoo/addons/sale_stock_picking_blocking/i18n/da.po
odoo/addons/sale_stock_picking_blocking/i18n/de.po
odoo/addons/sale_stock_picking_blocking/i18n/el_GR.po
odoo/addons/sale_stock_picking_blocking/i18n/en_GB.po
odoo/addons/sale_stock_picking_blocking/i18n/es.po
odoo/addons/sale_stock_picking_blocking/i18n/es_AR.po
odoo/addons/sale_stock_picking_blocking/i18n/es_CL.po
odoo/addons/sale_stock_picking_blocking/i18n/es_CO.po
odoo/addons/sale_stock_picking_blocking/i18n/es_CR.po
odoo/addons/sale_stock_picking_blocking/i18n/es_DO.po
odoo/addons/sale_stock_picking_blocking/i18n/es_EC.po
odoo/addons/sale_stock_picking_blocking/i18n/es_ES.po
odoo/addons/sale_stock_picking_blocking/i18n/es_MX.po
odoo/addons/sale_stock_picking_blocking/i18n/es_PE.po
odoo/addons/sale_stock_picking_blocking/i18n/es_PY.po
odoo/addons/sale_stock_picking_blocking/i18n/es_VE.po
odoo/addons/sale_stock_picking_blocking/i18n/et.po
odoo/addons/sale_stock_picking_blocking/i18n/eu.po
odoo/addons/sale_stock_picking_blocking/i18n/fa.po
odoo/addons/sale_stock_picking_blocking/i18n/fi.po
odoo/addons/sale_stock_picking_blocking/i18n/fr.po
odoo/addons/sale_stock_picking_blocking/i18n/fr_CA.po
odoo/addons/sale_stock_picking_blocking/i18n/fr_CH.po
odoo/addons/sale_stock_picking_blocking/i18n/gl.po
odoo/addons/sale_stock_picking_blocking/i18n/gl_ES.po
odoo/addons/sale_stock_picking_blocking/i18n/he.po
odoo/addons/sale_stock_picking_blocking/i18n/hr.po
odoo11_addon_sale_stock_picking_blocking-11.0.1.0.0.99.dev11.dist-info/METADATA
odoo11_addon_sale_stock_picking_blocking-11.0.1.0.0.99.dev11.dist-info/WHEEL
odoo11_addon_sale_stock_picking_blocking-11.0.1.0.0.99.dev11.dist-info/top_level.txt
odoo11_addon_sale_stock_picking_blocking-11.0.1.0.0.99.dev11.dist-info/RECORD
